uuidtool/__init__.py
uuidtool/cli.py
uuidtool/utils.py
uuidtool/commands/__init__.py
uuidtool/commands/edit.py
uuidtool/commands/info.py
uuidtool/commands/new.py
uuidtool/commands/range.py
uuidtool/commands/sandwich.py
uuidtool-1.4.dist-info/LICENSE
uuidtool-1.4.dist-info/METADATA
uuidtool-1.4.dist-info/WHEEL
uuidtool-1.4.dist-info/entry_points.txt
uuidtool-1.4.dist-info/top_level.txt
uuidtool-1.4.dist-info/RECORD
