Metadata-Version: 2.1
Name: uuidtool
Version: 1.4
Summary: CLI tool to manipulate UUIDs
Home-page: https://github.com/crazycat256/uuidtool
Author: crazycat256
Classifier: Programming Language :: Python :: 3
Classifier: License :: OSI Approved :: MIT License
Classifier: Operating System :: OS Independent
Classifier: Development Status :: 5 - Production/Stable
Classifier: Intended Audience :: Developers
Classifier: Topic :: Software Development :: Libraries :: Python Modules
Requires-Python: >=3.9
License-File: LICENSE
